astair/DNA_sequences_operations.py
astair/__init__.py
astair/aligner.py
astair/bam_file_parser.py
astair/caller.py
astair/cigar_search.py
astair/context_search.py
astair/filter.py
astair/finder.py
astair/idbiaser.py
astair/mbias.py
astair/phred.py
astair/safe_division.py
astair/simple_fasta_parser.py
astair/simulator.py
astair/statistics_summary.py
astair/summary.py
astair/vcf_reader.py
astair/version.py
scripts/__init__.py
scripts/run.py
asTair-3.3.2.dist-info/LICENSE.txt
asTair-3.3.2.dist-info/METADATA
asTair-3.3.2.dist-info/WHEEL
asTair-3.3.2.dist-info/entry_points.txt
asTair-3.3.2.dist-info/top_level.txt
asTair-3.3.2.dist-info/RECORD
