Metadata-Version: 2.1
Name: asTair
Version: 3.3.2
Summary: A tool for the analysis of bisulfite-free and base-resolution sequencing data generated with TET Assisted Pyridine borane Sequencing (TAPS), or other modified cytosine to thymine conversion methods (mCtoT). It also has some features for bisulfite sequencing data (unmodified cytosine to thymine conversion methods, CtoT).
Home-page: https://bitbucket.org/bsblabludwig/astair/
Author: Gergana V. Velikova and Benjamin Schuster-Boeckler
Author-email: gergana_velikova@yahoo.com
License: GPLv3
Keywords: TAPS taps cytosine caller methylation modification WGBS RRBS bisulfite epigenetics
Platform: UNKNOWN
Classifier: Programming Language :: Python :: 2.7
Classifier: Programming Language :: Python :: 3.5
Classifier: Programming Language :: Python :: 3.6
Classifier: Programming Language :: Python :: 3.7
Classifier: Intended Audience :: Science/Research
Classifier: Topic :: Scientific/Engineering :: Bio-Informatics
Requires-Python: >=2.7, !=3.0.*, !=3.1.*, !=3.2.*, !=3.3.*, !=3.4.*, < 4
Requires-Dist: Click (<8,>=7)
Requires-Dist: pysam (>=0.15.0)
Requires-Dist: pyahocorasick (<2,>=1)
Requires-Dist: numpy (<2,>=1)
Provides-Extra: plot
Requires-Dist: matplotlib ; extra == 'plot'
